instructlab/training/__init__.py
instructlab/training/_version.py
instructlab/training/accelerator.py
instructlab/training/async_logger.py
instructlab/training/batch_loss_manager.py
instructlab/training/batch_packer.py
instructlab/training/config.py
instructlab/training/data_process.py
instructlab/training/gpt_oss_utils_correct.py
instructlab/training/logger.py
instructlab/training/main_ds.py
instructlab/training/model.py
instructlab/training/padded_batch_packer.py
instructlab/training/sampler.py
instructlab/training/tokenizer_utils.py
instructlab/training/type_definitions.py
instructlab/training/utils.py
instructlab/training/chat_templates/ibm_generic_tmpl.py
instructlab/training/chat_templates/ibm_legacy_tmpl.py
instructlab/training/chat_templates/mistral_tmpl.py
instructlab/training/chat_templates/utils.py
instructlab_training-0.13.0.dist-info/licenses/LICENSE
instructlab_training-0.13.0.dist-info/METADATA
instructlab_training-0.13.0.dist-info/WHEEL
instructlab_training-0.13.0.dist-info/top_level.txt
instructlab_training-0.13.0.dist-info/RECORD
