Metadata-Version: 2.4
Name: instructlab-training
Version: 0.13.0
Summary: Training Library
Author-email: InstructLab <dev@instructlab.ai>
License: Apache-2.0
Project-URL: homepage, https://instructlab.ai
Project-URL: source, https://github.com/instructlab/training
Project-URL: issues, https://github.com/instructlab/training/issues
Classifier: Development Status :: 3 - Alpha
Classifier: Environment :: Console
Classifier: License :: OSI Approved :: Apache Software License
Classifier: License :: OSI Approved :: MIT License
Classifier: Operating System :: MacOS :: MacOS X
Classifier: Operating System :: POSIX :: Linux
Classifier: Topic :: Scientific/Engineering :: Artificial Intelligence
Classifier: Programming Language :: Python :: 3
Classifier: Programming Language :: Python :: 3.11
Classifier: Programming Language :: Python :: 3.12
Classifier: Programming Language :: Python :: 3.13
Classifier: Programming Language :: Python :: Implementation :: CPython
Requires-Python: >=3.11
License-File: LICENSE
Requires-Dist: packaging>=20.9
Requires-Dist: wheel>=0.43
Requires-Dist: pyyaml
Requires-Dist: py-cpuinfo
Requires-Dist: torch>=2.6.0
Requires-Dist: transformers>=4.55.0
Requires-Dist: datasets>=2.15.0
Requires-Dist: numba>=0.62.0
Requires-Dist: numpy>=1.26.4
Requires-Dist: rich
Requires-Dist: trl>=0.9.4
Requires-Dist: peft
Requires-Dist: pydantic>=2.7.0
Requires-Dist: aiofiles>=23.2.1
Provides-Extra: cuda
Requires-Dist: flash-attn>=2.4.0; extra == "cuda"
Requires-Dist: bitsandbytes>=0.43.1; extra == "cuda"
Requires-Dist: kernels>=0.9.0; extra == "cuda"
Requires-Dist: accelerate>=0.34.2; extra == "cuda"
Requires-Dist: liger-kernel>=0.5.10; extra == "cuda"
Requires-Dist: mamba-ssm[causal-conv1d]>=2.2.5; extra == "cuda"
Provides-Extra: rocm
Requires-Dist: flash-attn>=2.6.2; extra == "rocm"
Requires-Dist: accelerate>=0.34.2; extra == "rocm"
Requires-Dist: mamba-ssm[causal-conv1d]>=2.2.5; extra == "rocm"
Provides-Extra: hpu
Provides-Extra: deepspeed
Requires-Dist: deepspeed>=0.14.3; extra == "deepspeed"
Dynamic: license-file
